msgbox/__init__.py
msgbox/extended.py
msgbox-0.6.0.dist-info/METADATA
msgbox-0.6.0.dist-info/WHEEL
msgbox-0.6.0.dist-info/top_level.txt
msgbox-0.6.0.dist-info/RECORD
