Metadata-Version: 2.1
Name: msgbox
Version: 0.6.0
Summary: msgbox
Home-page: UNKNOWN
Author: UNKNOWN
Author-email: UNKNOWN
License: UNKNOWN
Platform: UNKNOWN
